krcf-0.4.0.dist-info/METADATA
krcf-0.4.0.dist-info/WHEEL
krcf-0.4.0.dist-info/licenses/LICENSE
krcf/__init__.py
krcf/krcf.pyi
krcf/krcf.pypy311-pp73-win_amd64.pyd
krcf/options.py
krcf/py.typed
krcf/types.py
krcf-0.4.0.dist-info/RECORD
