Metadata-Version: 2.4
Name: krcf
Version: 0.4.0
Classifier: Programming Language :: Python :: Implementation :: CPython
Classifier: Programming Language :: Python :: Implementation :: PyPy
Classifier: Programming Language :: Rust
Classifier: Topic :: Scientific/Engineering :: Artificial Intelligence
Requires-Dist: typing-extensions ; python_full_version < '3.11'
Requires-Dist: hypothesis[pytest,numpy] ; extra == 'test'
Requires-Dist: pytest-pretty ; extra == 'test'
Requires-Dist: pytest-xdist ; extra == 'test'
Requires-Dist: pytest-benchmark ; extra == 'test'
Requires-Dist: syrupy ; extra == 'test'
Requires-Dist: jsonpickle ; extra == 'test'
Requires-Dist: msgpack ; extra == 'test'
Provides-Extra: test
License-File: LICENSE
Summary: AWS Random Cut Forest for Python
Keywords: anomaly detection,random cut forest,rcf
Author-email: Dowon <ks2515@naver.com>
License-Expression: Apache-2.0
Requires-Python: >=3.10
Project-URL: source, https://github.com/Bing-su/krcf
